layrz_protocol/__init__.py
layrz_protocol/client.py
layrz_protocol/constants.py
layrz_protocol/py.typed
layrz_protocol/packets/__init__.py
layrz_protocol/packets/base.py
layrz_protocol/packets/ai/__init__.py
layrz_protocol/packets/ai/base.py
layrz_protocol/packets/ai/im.py
layrz_protocol/packets/client/__init__.py
layrz_protocol/packets/client/base.py
layrz_protocol/packets/client/pa.py
layrz_protocol/packets/client/pb.py
layrz_protocol/packets/client/pc.py
layrz_protocol/packets/client/pd.py
layrz_protocol/packets/client/pi.py
layrz_protocol/packets/client/pm.py
layrz_protocol/packets/client/pr.py
layrz_protocol/packets/client/ps.py
layrz_protocol/packets/definitions/__init__.py
layrz_protocol/packets/definitions/ble_advertisement.py
layrz_protocol/packets/definitions/ble_data.py
layrz_protocol/packets/definitions/ble_manufacturer_data.py
layrz_protocol/packets/definitions/ble_service_data.py
layrz_protocol/packets/definitions/command.py
layrz_protocol/packets/definitions/firmware_branch.py
layrz_protocol/packets/definitions/position.py
layrz_protocol/packets/server/__init__.py
layrz_protocol/packets/server/ab.py
layrz_protocol/packets/server/ac.py
layrz_protocol/packets/server/ao.py
layrz_protocol/packets/server/ar.py
layrz_protocol/packets/server/as_.py
layrz_protocol/packets/server/au.py
layrz_protocol/packets/server/base.py
layrz_protocol/packets/trips/__init__.py
layrz_protocol/packets/trips/base.py
layrz_protocol/packets/trips/te.py
layrz_protocol/packets/trips/ts.py
layrz_protocol/utils/__init__.py
layrz_protocol/utils/crc.py
layrz_protocol/utils/exceptions.py
layrz_protocol/utils/parsers.py
layrz_protocol-3.0.7.dist-info/licenses/LICENSE
layrz_protocol-3.0.7.dist-info/METADATA
layrz_protocol-3.0.7.dist-info/WHEEL
layrz_protocol-3.0.7.dist-info/top_level.txt
layrz_protocol-3.0.7.dist-info/RECORD
