Metadata-Version: 2.4
Name: layrz-protocol
Version: 3.0.7
Summary: Layrz Protocol wrapper, allows to send or translate the messages from and to the Layrz Protocol
Author-email: "Golden M, Inc." <software@goldenm.com>
Maintainer-email: Kenny Mochizuki <kenny@goldenm.com>, Jose Prieto <jprieto@goldenm.com>
License-Expression: Apache-2.0
Project-URL: Repository, https://github.com/goldenm-software/layrz-protocol
Project-URL: Changelog, https://github.com/goldenm-software/layrz-protocol/blob/main/CHANGELOG.md
Keywords: goldenm,layrz protocol,layrz,hub one,hubone
Classifier: Programming Language :: Python :: 3
Classifier: Programming Language :: Python :: 3.10
Classifier: Programming Language :: Python :: 3.11
Classifier: Programming Language :: Python :: 3.12
Classifier: Programming Language :: Python :: 3.13
Classifier: Programming Language :: Python :: 3.14
Classifier: Operating System :: OS Independent
Classifier: Development Status :: 5 - Production/Stable
Classifier: Intended Audience :: Developers
Requires-Python: >=3.10
License-File: LICENSE
Requires-Dist: deprecated>=1.2.18
Requires-Dist: pydantic>=2.10.6
Requires-Dist: requests>=2.32.3
Requires-Dist: typing-extensions>=4.12.2
Requires-Dist: tzdata>=2025.1
Dynamic: license-file
